projectdavid/__init__.py
projectdavid/_version.py
projectdavid/decorators.py
projectdavid/entity.py
projectdavid/events.py
projectdavid/serializers.py
projectdavid/clients/actions_client.py
projectdavid/clients/api_key_client.py
projectdavid/clients/assistants_client.py
projectdavid/clients/base_client.py
projectdavid/clients/base_vector_store.py
projectdavid/clients/file_processor.py
projectdavid/clients/file_search.py
projectdavid/clients/files_client.py
projectdavid/clients/inference_client.py
projectdavid/clients/messages_client.py
projectdavid/clients/runs.py
projectdavid/clients/synchronous_inference_wrapper.py
projectdavid/clients/threads_client.py
projectdavid/clients/users_client.py
projectdavid/clients/vector_store_manager.py
projectdavid/clients/vectors.py
projectdavid/clients/vision-file_processor.py
projectdavid/clients/vision_vectors.py
projectdavid/constants/platform.py
projectdavid/services/logging_service.py
projectdavid/synthesis/__init__.py
projectdavid/synthesis/llm_synthesizer.py
projectdavid/synthesis/prompt.py
projectdavid/synthesis/reranker.py
projectdavid/synthesis/retriever.py
projectdavid/utils/__init__.py
projectdavid/utils/function_call_suppressor.py
projectdavid/utils/monitor_launcher.py
projectdavid/utils/run_monitor.py
projectdavid/utils/vector_search_formatter.py
projectdavid-1.41.15.dist-info/licenses/LICENSE
projectdavid-1.41.15.dist-info/METADATA
projectdavid-1.41.15.dist-info/WHEEL
projectdavid-1.41.15.dist-info/top_level.txt
projectdavid-1.41.15.dist-info/RECORD
