Metadata-Version: 2.4
Name: projectdavid
Version: 1.41.15
Summary: Python SDK for interacting with the Entities Assistant API.
Author-email: Francis Neequaye Armah <francis.neequaye@projectdavid.co.uk>
License: PolyForm Noncommercial License 1.0.0
Keywords: AI,SDK,Entities,LLM,Assistant
Classifier: Development Status :: 4 - Beta
Classifier: Programming Language :: Python :: 3
Classifier: Programming Language :: Python :: 3.10
Classifier: Programming Language :: Python :: 3.11
Classifier: Programming Language :: Python :: 3.12
Classifier: License :: OSI Approved :: MIT License
Classifier: Operating System :: OS Independent
Requires-Python: >=3.9
License-File: LICENSE
Requires-Dist: httpx<0.29,>=0.25.2
Requires-Dist: pydantic<3.0,>=2.0
Requires-Dist: python-dotenv<2.0,>=1.0.1
Requires-Dist: aiofiles<25.0,>=23.2.1
Requires-Dist: ollama<0.5.0,>=0.4.4
Requires-Dist: projectdavid_common==0.21.9
Requires-Dist: qdrant-client<2.0.0,>=1.0.0
Requires-Dist: pdfplumber<0.12.0,>=0.11.0
Requires-Dist: validators<0.35.0,>=0.29.0
Requires-Dist: sentence-transformers<5.0,>=3.4.0
Requires-Dist: sseclient-py
Requires-Dist: requests
Requires-Dist: python-docx
Requires-Dist: python-pptx
Provides-Extra: dev
Requires-Dist: black>=23.3; extra == "dev"
Requires-Dist: isort>=5.12; extra == "dev"
Requires-Dist: pytest>=7.2; extra == "dev"
Requires-Dist: mypy>=1.0; extra == "dev"
Requires-Dist: build; extra == "dev"
Requires-Dist: twine; extra == "dev"
Dynamic: license-file
